fixcore/__init__.py
fixcore/__main__.py
fixcore/async_extensions.py
fixcore/compat.py
fixcore/console_renderer.py
fixcore/constants.py
fixcore/core_config.py
fixcore/dependencies.py
fixcore/error.py
fixcore/ids.py
fixcore/message_bus.py
fixcore/metrics.py
fixcore/service.py
fixcore/system_start.py
fixcore/types.py
fixcore/util.py
fixcore/validator.py
fixcore/worker_task_queue.py
fixcore/action_handlers/__init__.py
fixcore/action_handlers/merge_deferred_edge_handler.py
fixcore/analytics/__init__.py
fixcore/analytics/posthog.py
fixcore/analytics/recurrent_events.py
fixcore/cli/__init__.py
fixcore/cli/cli.py
fixcore/cli/command.py
fixcore/cli/model.py
fixcore/cli/tip_of_the_day.py
fixcore/config/__init__.py
fixcore/config/config_handler_service.py
fixcore/config/config_override_service.py
fixcore/config/core_config_handler.py
fixcore/db/__init__.py
fixcore/db/arango_query.py
fixcore/db/arango_query_rewrite.py
fixcore/db/arangodb_extensions.py
fixcore/db/arangodb_functions.py
fixcore/db/async_arangodb.py
fixcore/db/configdb.py
fixcore/db/db_access.py
fixcore/db/deferrededgesdb.py
fixcore/db/entitydb.py
fixcore/db/graphdb.py
fixcore/db/jobdb.py
fixcore/db/lockdb.py
fixcore/db/model.py
fixcore/db/modeldb.py
fixcore/db/packagedb.py
fixcore/db/reportdb.py
fixcore/db/runningtaskdb.py
fixcore/db/system_data_db.py
fixcore/db/templatedb.py
fixcore/db/timeseriesdb.py
fixcore/db/usagedb.py
fixcore/graph_manager/__init__.py
fixcore/graph_manager/graph_manager.py
fixcore/infra_apps/__init__.py
fixcore/infra_apps/local_runtime.py
fixcore/infra_apps/manifest.py
fixcore/infra_apps/package_manager.py
fixcore/infra_apps/runtime.py
fixcore/jupyterlite/bootstrap.js
fixcore/jupyterlite/config-utils.js
fixcore/jupyterlite/icon-120x120.png
fixcore/jupyterlite/icon-512x512.png
fixcore/jupyterlite/index.html
fixcore/jupyterlite/jupyter-lite.ipynb
fixcore/jupyterlite/jupyter-lite.json
fixcore/jupyterlite/jupyterlite.schema.v0.json
fixcore/jupyterlite/manifest.webmanifest
fixinventorycore-4.2.0.dist-info/METADATA
fixinventorycore-4.2.0.dist-info/WHEEL
fixinventorycore-4.2.0.dist-info/entry_points.txt
fixinventorycore-4.2.0.dist-info/top_level.txt
fixinventorycore-4.2.0.dist-info/RECORD
